pygarg/__init__.py
pygarg/__main__.py
pygarg/dung/__init__.py
pygarg/dung/apx_parser.py
pygarg/dung/dimacs_parser.py
pygarg/dung/encoding.py
pygarg/dung/solver.py
pygarg-1.0.2.dist-info/METADATA
pygarg-1.0.2.dist-info/WHEEL
pygarg-1.0.2.dist-info/licenses/LICENSE
pygarg-1.0.2.dist-info/RECORD
