Metadata-Version: 2.3
Name: pygarg
Version: 1.0.2
Summary: A Python enGine for Argumentation
Project-URL: Homepage, https://github.com/jgmailly/pygarg
Project-URL: Issues, https://github.com/jgmailly/pygarg/issues
Author-email: Jean-Guy Mailly <jean-guy.mailly@irit.fr>
License-File: LICENSE
Classifier: License :: OSI Approved :: GNU Lesser General Public License v3 (LGPLv3)
Classifier: Operating System :: OS Independent
Classifier: Programming Language :: Python :: 3
Requires-Python: >=3.9.6
